HiCPlot/Cli.py
HiCPlot/DiffSquHeatmap.py
HiCPlot/DiffSquHeatmapTrans.py
HiCPlot/NGStrack.py
HiCPlot/SquHeatmap.py
HiCPlot/SquHeatmapTrans.py
HiCPlot/TriHeatmap.py
HiCPlot/__init__.py
HiCPlot/__main__.py
HiCPlot/_version.py
HiCPlot/upper_lower_triangle_heatmap.py
hicplot-1.49.dist-info/LICENSE
hicplot-1.49.dist-info/METADATA
hicplot-1.49.dist-info/WHEEL
hicplot-1.49.dist-info/entry_points.txt
hicplot-1.49.dist-info/top_level.txt
hicplot-1.49.dist-info/RECORD
