Metadata-Version: 2.1
Name: hicplot
Version: 1.49
Summary: Plot Hi-C heatmaps and genomic tracks.
Home-page: https://github.com/BenxiaHu/HiCPlot
Author: Benxia Hu
Author-email: hubenxia@gmail.com
Classifier: Programming Language :: Python :: 3
Classifier: License :: OSI Approved :: MIT License
Classifier: Operating System :: OS Independent
Requires-Python: >=3.12
License-File: LICENSE
Requires-Dist: numpy
Requires-Dist: pandas
Requires-Dist: matplotlib
Requires-Dist: pyBigWig
Requires-Dist: pyranges
Requires-Dist: cooler
